todoist/__init__.py
todoist/api.py
todoist/models.py
todoist/managers/__init__.py
todoist/managers/activity.py
todoist/managers/archive.py
todoist/managers/backups.py
todoist/managers/biz_invitations.py
todoist/managers/business_users.py
todoist/managers/collaborator_states.py
todoist/managers/collaborators.py
todoist/managers/completed.py
todoist/managers/emails.py
todoist/managers/filters.py
todoist/managers/generic.py
todoist/managers/invitations.py
todoist/managers/items.py
todoist/managers/labels.py
todoist/managers/live_notifications.py
todoist/managers/locations.py
todoist/managers/notes.py
todoist/managers/projects.py
todoist/managers/quick.py
todoist/managers/reminders.py
todoist/managers/sections.py
todoist/managers/templates.py
todoist/managers/uploads.py
todoist/managers/user.py
todoist/managers/user_settings.py
todoist_python-8.1.4.dist-info/LICENSE
todoist_python-8.1.4.dist-info/METADATA
todoist_python-8.1.4.dist-info/WHEEL
todoist_python-8.1.4.dist-info/top_level.txt
todoist_python-8.1.4.dist-info/RECORD
