Metadata-Version: 2.1
Name: todoist-python
Version: 8.1.4
Summary: todoist-python - The official Todoist Python API library
Author: Doist Team
Author-email: integrations@todoist.com
License: MIT
Classifier: Intended Audience :: Developers
Classifier: License :: OSI Approved :: MIT License
Classifier: Programming Language :: Python
License-File: LICENSE
